ngtpy.cpython-311-darwin.so
ngt.dylibs/libomp.dylib
ngt-2.3.12.dist-info/RECORD
ngt-2.3.12.dist-info/LICENSE
ngt-2.3.12.dist-info/WHEEL
ngt-2.3.12.dist-info/top_level.txt
ngt-2.3.12.dist-info/METADATA
