Metadata-Version: 2.1
Name: ngt
Version: 2.3.12
Summary: python NGT
Home-page: https://github.com/yahoojapan/NGT
Author: Yahoo! JAPAN research
Author-email: miwasaki@yahoo-corp.jp
License: Apache License Version 2.0
Platform: UNKNOWN
Requires-Dist: numpy
